PLMinteract/__init__.py
PLMinteract/__main__.py
PLMinteract/inference_PPI.py
PLMinteract/mutation_predict.py
PLMinteract/mutation_train.py
PLMinteract/predict_ddp.py
PLMinteract/train_binary.py
PLMinteract/train_mlm.py
PLMinteract/inference/inference_PPI_singleGPU.py
PLMinteract/inference/toy_inference.py
PLMinteract/utils/data_load.py
PLMinteract/utils/ddp.py
PLMinteract/utils/metrics.py
plminteract-0.1.1.dist-info/licenses/LICENSE
plminteract-0.1.1.dist-info/METADATA
plminteract-0.1.1.dist-info/WHEEL
plminteract-0.1.1.dist-info/entry_points.txt
plminteract-0.1.1.dist-info/top_level.txt
plminteract-0.1.1.dist-info/RECORD
