Metadata-Version: 2.4
Name: PLMinteract
Version: 0.1.1
Summary: PLM-interact: extending protein language models to predict protein-protein interactions
Author-email: Dan Liu <liudan12260@gmail.com>
License-Expression: MIT
Project-URL: Homepage, https://github.com/liudan111/PLM-interact
Project-URL: Issues, https://github.com/liudan111/PLM-interact/issues
Classifier: Programming Language :: Python :: 3
Requires-Python: >=3.10
License-File: LICENSE
Requires-Dist: transformers==4.40.1
Requires-Dist: sentence_transformers
Requires-Dist: datasets
Requires-Dist: scipy
Requires-Dist: numpy
Requires-Dist: pandas
Requires-Dist: torch>=2.0.1
Requires-Dist: matplotlib
Requires-Dist: biopython
Requires-Dist: seaborn
Requires-Dist: scikit-learn
Requires-Dist: huggingface_hub
Dynamic: license-file
